D3ApiRef/README.md
D3ApiRef/__init__.py
D3ApiRef/__main__.py
D3ApiRef/file.epub
D3ApiRef/index.html
D3ApiRef/css/__init__.py
D3ApiRef/css/annotations.css
D3ApiRef/css/main.css
D3ApiRef/css/normalize.css
D3ApiRef/css/popup.css
D3ApiRef/font/__init__.py
D3ApiRef/font/fontello.eot
D3ApiRef/font/fontello.svg
D3ApiRef/font/fontello.ttf
D3ApiRef/font/fontello.woff
D3ApiRef/img/__init__.py
D3ApiRef/img/annotator-glyph-sprite.png
D3ApiRef/img/annotator-icon-sprite.png
D3ApiRef/img/apple-touch-icon.png
D3ApiRef/img/cancelfullscreen.png
D3ApiRef/img/close.png
D3ApiRef/img/fullscreen.png
D3ApiRef/img/loader.gif
D3ApiRef/img/menu-icon.png
D3ApiRef/img/save.png
D3ApiRef/img/saved.png
D3ApiRef/img/settings-s.png
D3ApiRef/img/settings.png
D3ApiRef/img/star.png
D3ApiRef/js/__init__.py
D3ApiRef/js/epub.js
D3ApiRef/js/epub.min.js
D3ApiRef/js/epub.min.map
D3ApiRef/js/hooks.min.js
D3ApiRef/js/hooks.min.map
D3ApiRef/js/reader.js
D3ApiRef/js/reader.js.map
D3ApiRef/js/reader.min.js
D3ApiRef/js/reader.min.map
D3ApiRef/js/hooks/__init__.py
D3ApiRef/js/hooks/extensions/__init__.py
D3ApiRef/js/hooks/extensions/highlight.js
D3ApiRef/js/libs/__init__.py
D3ApiRef/js/libs/jquery.min.js
D3ApiRef/js/libs/localforage.min.js
D3ApiRef/js/libs/screenfull.js
D3ApiRef/js/libs/screenfull.min.js
D3ApiRef/js/libs/zip.min.js
D3ApiRef/js/plugins/__init__.py
D3ApiRef/js/plugins/hypothesis.js
D3ApiRef/js/plugins/search.js
d3_api_ref-2024.3.1.0.dist-info/METADATA
d3_api_ref-2024.3.1.0.dist-info/WHEEL
d3_api_ref-2024.3.1.0.dist-info/entry_points.txt
d3_api_ref-2024.3.1.0.dist-info/top_level.txt
d3_api_ref-2024.3.1.0.dist-info/RECORD
